{
  "id": "IA.L2-3.5.10",
  "control_number": "IA.L2-3.5.10",
  "title": "Store and Transmit Only Cryptographically Protected Passwords",
  "description": "Store and transmit only cryptographically-protected passwords.",
  "category": "IA",
  "target_os": [
    "debian",
    "linux",
    "windows_client",
    "windows_server"
  ],
  "check_details": {
    "windows_client": {
      "checks": [
        {
          "check_type": "command",
          "name": "LM Password Hashing is Disabled",
          "sub_control": "a",
          "command": "cs_f(identification_authentication.lm_hash_disabled_wc)",
          "expected_result": "True",
          "purpose": "Verify LM hash storage is disabled via the Network security: Do not store LAN Manager hash value on next password change GPO setting"
        },
        {
          "check_type": "command",
          "name": "Reversible Encryption is Disabled",
          "sub_control": "b",
          "command": "cs_f(identification_authentication.reversible_encryption_disabled_wc)",
          "expected_result": "True",
          "purpose": "Confirm Store password using reversible encryption is disabled in the local or domain password policy"
        },
        {
          "check_type": "command",
          "name": "Authentication Traffic is Encrypted in Transit",
          "sub_control": "c",
          "command": "cs_f(identification_authentication.auth_traffic_encrypted_wc)",
          "expected_result": "True",
          "purpose": "Verify LDAP signing and channel binding are enforced and Kerberos is used for network authentication to protect credentials in transit"
        }
      ]
    },
    "windows_server": {
      "checks": [
        {
          "check_type": "command",
          "name": "LM Password Hashing is Disabled",
          "sub_control": "a",
          "command": "cs_f(identification_authentication.lm_hash_disabled_ws)",
          "expected_result": "True",
          "purpose": "Verify LM hash storage is disabled via GPO on the server"
        },
        {
          "check_type": "command",
          "name": "Reversible Encryption is Disabled",
          "sub_control": "b",
          "command": "cs_f(identification_authentication.reversible_encryption_disabled_ws)",
          "expected_result": "True",
          "purpose": "Confirm Store password using reversible encryption is disabled in the domain password policy"
        },
        {
          "check_type": "command",
          "name": "LDAP Signing is Required",
          "sub_control": "c",
          "command": "cs_f(identification_authentication.ldap_signing_ws)",
          "expected_result": "True",
          "purpose": "Verify Domain controller: LDAP server signing requirements is set to Require signing to protect credential data in LDAP traffic"
        },
        {
          "check_type": "command",
          "name": "Protected Users Security Group is Utilized for Privileged Accounts",
          "sub_control": "d",
          "command": "cs_f(identification_authentication.protected_users_group_ws)",
          "expected_result": "True",
          "purpose": "Confirm privileged accounts are members of the Protected Users security group to enforce strong credential protection (no NTLM, no RC4, no credential caching)"
        }
      ]
    },
    "linux": {
      "checks": [
        {
          "check_type": "command",
          "name": "Passwords are Hashed with SHA-512 or Yescrypt",
          "sub_control": "a",
          "command": "cs_f(identification_authentication.shadow_hash_algorithm_lx)",
          "expected_result": "True",
          "purpose": "Verify passwords in /etc/shadow are hashed with SHA-512 ($6$) or yescrypt ($y$) and no MD5 ($1$) or DES hashes are present"
        },
        {
          "check_type": "command",
          "name": "PAM is Configured to Use Strong Password Hashing",
          "sub_control": "b",
          "command": "cs_f(identification_authentication.pam_hashing_lx)",
          "expected_result": "True",
          "purpose": "Confirm pam_unix.so in /etc/pam.d/common-password uses sha512 or yescrypt hashing algorithm"
        },
        {
          "check_type": "command",
          "name": "SSH Transmits Credentials Only Over Encrypted Channels",
          "sub_control": "c",
          "command": "cs_f(identification_authentication.ssh_encryption_lx)",
          "expected_result": "True",
          "purpose": "Verify SSH uses strong encryption ciphers and all authentication is transmitted over an encrypted session"
        }
      ]
    },
    "debian": {
      "checks": [
        {
          "check_type": "command",
          "name": "Passwords are Hashed with SHA-512 or Yescrypt",
          "sub_control": "a",
          "command": "cs_f(identification_authentication.shadow_hash_algorithm_lx)",
          "expected_result": "True",
          "purpose": "Verify passwords in /etc/shadow use SHA-512 ($6$) or yescrypt ($y$) hashing on Debian"
        },
        {
          "check_type": "command",
          "name": "PAM is Configured to Use Strong Password Hashing",
          "sub_control": "b",
          "command": "cs_f(identification_authentication.pam_hashing_lx)",
          "expected_result": "True",
          "purpose": "Confirm pam_unix.so in /etc/pam.d/common-password uses sha512 or yescrypt on Debian"
        },
        {
          "check_type": "command",
          "name": "SSH Transmits Credentials Only Over Encrypted Channels",
          "sub_control": "c",
          "command": "cs_f(identification_authentication.ssh_encryption_lx)",
          "expected_result": "True",
          "purpose": "Verify SSH uses strong encryption ciphers for all authentication traffic on Debian"
        }
      ]
    }
  },
  "severity": "High",
  "remediation": "Disable LM hash storage via GPO. Disable reversible encryption in the password policy. Enable LDAP signing. Add privileged accounts to the Protected Users group. On Linux, configure PAM to use sha512 or yescrypt hashing and ensure no MD5 or DES hashes exist in /etc/shadow.",
  "tags": [
    "IA",
    "IA.L2-3.5.10"
  ]
}